CHANGES.txt
README.txt
setup.py
collective/__init__.py
collective.collage.portlets.egg-info/PKG-INFO
collective.collage.portlets.egg-info/SOURCES.txt
collective.collage.portlets.egg-info/dependency_links.txt
collective.collage.portlets.egg-info/entry_points.txt
collective.collage.portlets.egg-info/namespace_packages.txt
collective.collage.portlets.egg-info/not-zip-safe
collective.collage.portlets.egg-info/requires.txt
collective.collage.portlets.egg-info/top_level.txt
collective/collage/__init__.py
collective/collage/portlets/__init__.py
collective/collage/portlets/browser.py
collective/collage/portlets/column_portlets.pt
collective/collage/portlets/column_portlets_top.pt
collective/collage/portlets/configure.zcml
collective/collage/portlets/portlets.xml