Metadata-Version: 1.0
Name: collective.collage.portlets
Version: 0.3.1
Summary: Add-on that allows displaying portlets inside a collage.
Home-page: http://www.plone.org/products/collective.collage.portlets
Author: Malthe Borch
Author-email: mborch@gmail.com
License: GPL
Keywords: collage plone rss portlets
Platform: UNKNOWN
Classifier: Programming Language :: Python
Classifier: Framework :: Plone
Classifier: License :: OSI Approved :: GNU General Public License (GPL)
Classifier: Development Status :: 5 - Production/Stable
